flowrl
