Metadata-Version: 2.4
Name: flowrl
Version: 0.1.1
Summary: A library desgined for flow-based RL algorithms
Home-page: https://github.com/typoverflow/flow-rl
Author: typoverflow
Author-email: typoverflow@gmail.com
License: MIT
Requires-Python: >=3.11
License-File: LICENSE
Requires-Dist: jax[cuda12]==0.5.3
Requires-Dist: flax==0.10.5
Requires-Dist: gymnasium
Requires-Dist: gymnasium_robotics
Requires-Dist: shimmy==1.3.0
Requires-Dist: gym==0.23.1
Requires-Dist: mujoco_py==2.1.2.14
Requires-Dist: dm_control<=1.0.20
Requires-Dist: mujoco<=3.1.6
Requires-Dist: Cython<3
Requires-Dist: six==1.17.0
Requires-Dist: tqdm
Requires-Dist: hydra-core
Requires-Dist: distrax
Requires-Dist: tensorboardX==2.6.2.2
Requires-Dist: scikit-learn==1.6.1
Requires-Dist: wandb
Dynamic: author
Dynamic: author-email
Dynamic: description
Dynamic: description-content-type
Dynamic: home-page
Dynamic: license
Dynamic: license-file
Dynamic: requires-dist
Dynamic: requires-python
Dynamic: summary
